arka/__init__.py
arka/api.py
tests/__init__.py
tests/test_arka.py
arka_python-0.1.dist-info/LICENSE
arka_python-0.1.dist-info/METADATA
arka_python-0.1.dist-info/WHEEL
arka_python-0.1.dist-info/top_level.txt
arka_python-0.1.dist-info/RECORD
